GreenPonik_BLE/__init__.py
GreenPonik_BLE/advertisement.py
GreenPonik_BLE/bletools.py
GreenPonik_BLE/gattserver.py
GreenPonik_BLE/service.py
example/__init__.py
example/main.py
greenponik_ble-0.0.3.dist-info/METADATA
greenponik_ble-0.0.3.dist-info/WHEEL
greenponik_ble-0.0.3.dist-info/top_level.txt
greenponik_ble-0.0.3.dist-info/RECORD
