Metadata-Version: 2.1
Name: greenponik-ble
Version: 0.0.3
Summary: Bluetooth BLE python server
Home-page: https://github.com/GreenPonik/GreenPonik_BLE
Author: GreenPonik SAS
Author-email: contact@greenponik.com
License: MIT
Project-URL: Source, https://github.com/GreenPonik/GreenPonik_BLE/
Project-URL: Bug Reports, https://github.com/GreenPonik/GreenPonik_BLE/issues
Keywords: GreenPonik hydroponics bluetooth         BLE python hardware diy iot raspberry pi
Platform: UNKNOWN
Classifier: Programming Language :: Python :: 3
Classifier: License :: OSI Approved :: MIT License
Classifier: Operating System :: OS Independent
Requires-Python: >=3.7.0
Requires-Dist: Adafruit-PlatformDetect
